py_simple_readme/__init__.py
py_simple_readme/py_simple_readme.py
py_simple_readme-0.0.8.dist-info/LICENSE
py_simple_readme-0.0.8.dist-info/METADATA
py_simple_readme-0.0.8.dist-info/WHEEL
py_simple_readme-0.0.8.dist-info/top_level.txt
py_simple_readme-0.0.8.dist-info/RECORD
